partivision/__init__.py
partivision/app.py
partivision/annotation/__init__.py
partivision/annotation/auto_annotation.py
partivision/annotation/config.py
partivision/annotation/drawing.py
partivision/annotation/image_annotation.py
partivision/annotation/main.py
partivision/annotation/model.py
partivision/date_utils/__init__.py
partivision/date_utils/date_utils.py
partivision/inference/__init__.py
partivision/inference/config.py
partivision/inference/data_handler.py
partivision/inference/image_processing.py
partivision/inference/inference_pipeline.py
partivision/inference/main.py
partivision/inference/util.py
partivision/inference/weight_manager.py
partivision/plotting/__init__.py
partivision/plotting/updateable_plot.py
partivision/settings/__init__.py
partivision/settings/default_settings.json
partivision/settings/settings.py
partivision/temp/.gitkeep
partivision/training/__init__.py
partivision/training/configs.py
partivision/training/main.py
partivision/training/trainer.py
partivision/weights/.gitkeep
partivisionML-0.20.dist-info/LICENSE
partivisionML-0.20.dist-info/METADATA
partivisionML-0.20.dist-info/WHEEL
partivisionML-0.20.dist-info/entry_points.txt
partivisionML-0.20.dist-info/top_level.txt
partivisionML-0.20.dist-info/RECORD
