Metadata-Version: 2.1
Name: partivisionML
Version: 0.20
Summary: Computer Vision Package for Microfluidics. For more information, contact akaminer@gatech.edu.
Home-page: https://github.com/AndKaminer/PartiVisionML
Author: Andrew Kaminer
Author-email: akaminer@gatech.edu
License: UNKNOWN
Platform: UNKNOWN
License-File: LICENSE
Requires-Dist: boto3
Requires-Dist: dash
Requires-Dist: dash-bootstrap-components
Requires-Dist: diplib
Requires-Dist: easygui
Requires-Dist: huggingface-hub
Requires-Dist: numpy
Requires-Dist: opencv-python
Requires-Dist: roboflow
Requires-Dist: ultralytics
